Metadata-Version: 1.0
Name: scroodle
Version: 1.0
Summary: IDC Moodle scrapper
Home-page: UNKNOWN
Author: Tsehori
Author-email: g.tsehori@gmail.com
License: MIT
Platform: UNKNOWN
